streamlit_cosmograph/__init__.py
streamlit_cosmograph/app.py
streamlit_cosmograph/config.py
streamlit_cosmograph/layout.py
streamlit_cosmograph/link.py
streamlit_cosmograph/node.py
streamlit_cosmograph/utils.py
streamlit_cosmograph/frontend/build/asset-manifest.json
streamlit_cosmograph/frontend/build/bootstrap.min.css
streamlit_cosmograph/frontend/build/index.html
streamlit_cosmograph/frontend/build/static/css/main.b7f8e1ef.css
streamlit_cosmograph/frontend/build/static/css/main.b7f8e1ef.css.map
streamlit_cosmograph/frontend/build/static/js/main.2bd4c3be.js
streamlit_cosmograph/frontend/build/static/js/main.2bd4c3be.js.LICENSE.txt
streamlit_cosmograph/frontend/build/static/js/main.2bd4c3be.js.map
streamlit_cosmograph-0.1.1.dist-info/LICENSE
streamlit_cosmograph-0.1.1.dist-info/METADATA
streamlit_cosmograph-0.1.1.dist-info/WHEEL
streamlit_cosmograph-0.1.1.dist-info/top_level.txt
streamlit_cosmograph-0.1.1.dist-info/RECORD
