Metadata-Version: 2.1
Name: streamlit-cosmograph
Version: 0.1.1
Summary: Cosmograph for Streamlit.
Home-page: https://github.com/Wollents/streamlit-cosmograph.git
Author: Wollents(Wang Yang)
Author-email: yangwang0222@163.com
License: MIT
Requires-Python: >=3.8
License-File: LICENSE
Requires-Dist: streamlit>=0.63
Requires-Dist: scipy>=1.4.1
